README.md
crudest.py
setup.py
crudest.egg-info/PKG-INFO
crudest.egg-info/SOURCES.txt
crudest.egg-info/dependency_links.txt
crudest.egg-info/requires.txt
crudest.egg-info/top_level.txt
tests/__init__.py
tests/cat_api.py
tests/test_cats_api.py