Metadata-Version: 1.0
Name: crudest
Version: 0.10
Summary: CRUD-structured REST APIs in Python, using Flask, marshmallow, webargs and apispec
Home-page: https://github.com/trackuity/crudest
Author: UNKNOWN
Author-email: UNKNOWN
License: Apache Software License (ASF)
Platform: UNKNOWN
